{
  "cnj": "5004916-30.2024.8.13.0287",
  "_fontes_database": [
    "TJ-MG-2026.json"
  ],
  "status": "ok",
  "recuperanda_capa": "CONTINENTALBANCO NP FUNDO DE INVESTIMENTO EM DIREITOS CREDITORIOS NAO PADRONIZADOS X TEXTILNOVA FIACAO LTDA",
  "polos": {
    "ATIVO": [
      "CONTINENTALBANCO NP FUNDO DE INVESTIMENTO EM DIREITOS CREDITORIOS NAO PADRONIZADOS"
    ],
    "PASSIVO": [
      "TEXTILNOVA FIACAO LTDA"
    ]
  },
  "classe": "Falência de Empresários, Sociedades Empresáriais, Microempresas e Empresas de Pequeno Porte",
  "tribunal": "TJMG"
}